Metadata-Version: 1.0
Name: texploratory
Version: 0.1.0
Summary: Exploratory Data Analysis tools for text data
Home-page: https://github.com/miorgash/texploratory
Author: Miori Igarashi
Author-email: miorgash@gmail.com
License: MIT License
